jl_theme_light_minimal/__init__.py
jl_theme_light_minimal/_version.py
jl_theme_light_minimal-0.1.0.data/data/share/jupyter/labextensions/jl-theme-light-minimal/package.json
jl_theme_light_minimal-0.1.0.data/data/share/jupyter/labextensions/jl-theme-light-minimal/static/568.912f89e142ceeea95a1a.js
jl_theme_light_minimal-0.1.0.data/data/share/jupyter/labextensions/jl-theme-light-minimal/static/remoteEntry.952c5e50425a336c958f.js
jl_theme_light_minimal-0.1.0.data/data/share/jupyter/labextensions/jl-theme-light-minimal/static/style.js
jl_theme_light_minimal-0.1.0.data/data/share/jupyter/labextensions/jl-theme-light-minimal/static/third-party-licenses.json
jl_theme_light_minimal-0.1.0.data/data/share/jupyter/labextensions/jl-theme-light-minimal/themes/jl-theme-light-minimal/index.css
jl_theme_light_minimal-0.1.0.data/data/share/jupyter/labextensions/jl-theme-light-minimal/themes/jl-theme-light-minimal/index.js
jl_theme_light_minimal-0.1.0.data/data/share/jupyter/labextensions/jl-theme-light-minimal/install.json
jl_theme_light_minimal-0.1.0.dist-info/METADATA
jl_theme_light_minimal-0.1.0.dist-info/WHEEL
jl_theme_light_minimal-0.1.0.dist-info/licenses/LICENSE
jl_theme_light_minimal-0.1.0.dist-info/RECORD
