Metadata-Version: 2.1
Name: jl_theme_light_minimal
Version: 0.1.0
Summary: A JupyterLab theme which removes code cell background
Project-URL: Homepage, https://github.com/falconair/jl-theme-light-minimal
Project-URL: Bug Tracker, https://github.com/falconair/jl-theme-light-minimal/issues
Project-URL: Repository, https://github.com/falconair/jl-theme-light-minimal.git
Author-email: Shahbaz Chaudhary <shahbazc@gmail.com>
License: BSD 3-Clause License
License-File: LICENSE
Classifier: Framework :: Jupyter
Classifier: Framework :: Jupyter :: JupyterLab
Classifier: Framework :: Jupyter :: JupyterLab :: 3
Classifier: Framework :: Jupyter :: JupyterLab :: Extensions
Classifier: Framework :: Jupyter :: JupyterLab :: Extensions :: Prebuilt
Classifier: License :: OSI Approved :: BSD License
Classifier: Programming Language :: Python
Classifier: Programming Language :: Python :: 3
Classifier: Programming Language :: Python :: 3.7
Classifier: Programming Language :: Python :: 3.8
Classifier: Programming Language :: Python :: 3.9
Classifier: Programming Language :: Python :: 3.10
Classifier: Programming Language :: Python :: 3.11
Requires-Python: >=3.7
